httomo_backends/methods_database/backends/httomolib/httomolib.yaml
httomo_backends/methods_database/backends/httomolib/httomolib_modules.yaml
httomo_backends/methods_database/backends/httomolibgpu/__init__.py
httomo_backends/methods_database/backends/httomolibgpu/httomolibgpu.yaml
httomo_backends/methods_database/backends/httomolibgpu/httomolibgpu_modules.yaml
httomo_backends/methods_database/backends/tomopy/__init__.py
httomo_backends/methods_database/backends/tomopy/tomopy.yaml
httomo_backends/methods_database/backends/tomopy/tomopy_modules.yaml
httomo_backends/scripts/__init__.py
httomo_backends/scripts/yaml_templates_generator.py
httomo_backends/scripts/yaml_unsupported_tomopy_remove.py
httomo_backends/yaml_templates/httomo/httomo.data.hdf.loaders/standard_tomo.yaml
httomo_backends/yaml_templates/httomo/httomo.methods/calculate_stats.yaml
httomo_backends/yaml_templates/httomo/httomo.methods/save_intermediate_data.yaml
httomo_backends/yaml_templates/httomolib/httomolib.misc.images/save_to_images.yaml
httomo_backends/yaml_templates/httomolib/httomolib.misc.morph/data_reducer.yaml
httomo_backends/yaml_templates/httomolib/httomolib.misc.segm/binary_thresholding.yaml
httomo_backends/yaml_templates/httomolib/httomolib.prep.phase/paganin_filter.yaml
httomo_backends/yaml_templates/httomolibgpu/httomolibgpu.misc.corr/median_filter.yaml
httomo_backends/yaml_templates/httomolibgpu/httomolibgpu.misc.corr/remove_outlier.yaml
httomo_backends/yaml_templates/httomolibgpu/httomolibgpu.misc.morph/data_resampler.yaml
httomo_backends/yaml_templates/httomolibgpu/httomolibgpu.misc.morph/sino_360_to_180.yaml
httomo_backends/yaml_templates/httomolibgpu/httomolibgpu.misc.rescale/rescale_to_int.yaml
httomo_backends/yaml_templates/httomolibgpu/httomolibgpu.prep.alignment/distortion_correction_proj_discorpy.yaml
httomo_backends/yaml_templates/httomolibgpu/httomolibgpu.prep.normalize/normalize.yaml
httomo_backends/yaml_templates/httomolibgpu/httomolibgpu.prep.phase/paganin_filter_savu.yaml
httomo_backends-2.1.1.dist-info/LICENSE
httomo_backends-2.1.1.dist-info/METADATA
httomo_backends-2.1.1.dist-info/WHEEL
httomo_backends-2.1.1.dist-info/top_level.txt
httomo_backends-2.1.1.dist-info/RECORD
